travel/__init__.py
travel/thailand.py
travel/vietnam.py
travel_jay_for_fun/__init__.py
travel_jay_for_fun/thailand.py
travel_jay_for_fun/vietnam.py
travel_jay_for_fun-0.1.0.dist-info/METADATA
travel_jay_for_fun-0.1.0.dist-info/WHEEL
travel_jay_for_fun-0.1.0.dist-info/top_level.txt
travel_jay_for_fun-0.1.0.dist-info/RECORD
