Metadata-Version: 2.1
Name: travel-jay-for-fun
Version: 0.1.0
Summary: This package is just for fun and learning purposes.
Home-page: https://github.com/SeungJay/for_fun
Author: Jay
Author-email: ssj2515@gmail.com
License: UNKNOWN
Platform: UNKNOWN
Classifier: Programming Language :: Python :: 3
Classifier: License :: OSI Approved :: MIT License
Classifier: Operating System :: OS Independent
Requires-Python: >=3.6
